reverseengineering/__init__.py
reverseengineering/get_current_playback_docs.py
reverseengineering/get_playlist_example_res.py
reverseengineering/get_playlist_tracks_example_res.py
ytm_tui/__init__.py
ytm_tui/__main__.py
ytm_tui/__version__.py
ytm_tui/src/DeviceMenu.py
ytm_tui/src/LibraryList.py
ytm_tui/src/LibraryMenu.py
ytm_tui/src/Logging.py
ytm_tui/src/MainForm.py
ytm_tui/src/NowPlaying.py
ytm_tui/src/PlaylistMenu.py
ytm_tui/src/SearchInput.py
ytm_tui/src/TracksMenu.py
ytm_tui/src/__init__.py
ytm_tui/src/colors.py
ytm_tui/src/component.py
ytm_tui/src/config.py
ytm_tui/src/input.py
ytm_tui/src/menu.py
ytm_tui/src/ui.py
ytm_tui/src/util.py
ytm_tui/src/youtubeApi.py
ytm_tui-0.1.9.dist-info/LICENSE
ytm_tui-0.1.9.dist-info/METADATA
ytm_tui-0.1.9.dist-info/WHEEL
ytm_tui-0.1.9.dist-info/entry_points.txt
ytm_tui-0.1.9.dist-info/top_level.txt
ytm_tui-0.1.9.dist-info/RECORD
