Metadata-Version: 2.1
Name: ytm-tui
Version: 0.1.9
Summary: Youtube Music from the terminal
Home-page: https://github.com/BrownNPC/Youtube-Music-Tui
Author: BrownNPC
License: GPLv3+
Classifier: License :: OSI Approved :: GNU General Public License v3 or later (GPLv3+)
Classifier: Programming Language :: Python
Classifier: Programming Language :: Python :: 3
Classifier: Programming Language :: Python :: 3.10
Classifier: Programming Language :: Python :: Implementation :: CPython
Classifier: Programming Language :: Python :: Implementation :: PyPy
Requires-Python: >=3.10
License-File: LICENSE
Requires-Dist: ytmusicapi
Requires-Dist: toml
Requires-Dist: python-mpv
Provides-Extra: fancy_feature
Requires-Dist: curses ; extra == 'fancy_feature'
